momapper/__init__.py
momapper/fields.py
momapper/mappedclass.py
momapper/mongodb/__init__.py
momapper/mongodb/collection.py
momapper/mongodb/cursor.py
momapper/mongodb/manager.py
momapper/types.py
momapper-0.0.4.dist-info/LICENSE
momapper-0.0.4.dist-info/WHEEL
momapper-0.0.4.dist-info/METADATA
momapper-0.0.4.dist-info/RECORD
