Metadata-Version: 2.1
Name: momapper
Version: 0.0.4
Summary: Python Mapper for MongoDB models
Home-page: https://github.com/devilicecream/MoMapper
License: MIT
Author: Walter Danilo Galante
Author-email: walter.galante@ovalmoney.com
Requires-Python: >=3.6,<4
Classifier: Development Status :: 2 - Pre-Alpha
Classifier: Intended Audience :: Developers
Classifier: License :: OSI Approved :: MIT License
Classifier: Natural Language :: English
Classifier: Programming Language :: Python :: 3
Classifier: Programming Language :: Python :: 3.4
Classifier: Programming Language :: Python :: 3.5
Classifier: Programming Language :: Python :: 3.6
Classifier: Programming Language :: Python :: 3.7
Classifier: Programming Language :: Python :: 3.8
Requires-Dist: pymongo (>=3.10.1,<4.0.0)
Project-URL: Repository, https://github.com/devilicecream/MoMapper
